[{
  "title": "Just Go With It",
  "year": "2011",
  "url": "https://www.imdb.com//title/tt1564367/?ref_=fn_ft_tt_1",
  "genreList": [
    "Comedy",
    "Romance"
  ],
  "countryList": [
    "USA"
  ],
  "description": "Danny (Adam Sandler) must engage Katherine (Jennifer Aniston), his faithful assistant, to pretend to be his soon to be ex-wife. Danny must pretend that he is married, because he lied to his dream girl, Palmer (Brooklyn Decker) the most gorgeous woman in the world. To keep the woman he loves, covering up one lie soon turns into many lies.",
  "budget": "$80,000,000 (estimated)",
  "gross": "$214,945,591",
  "ratingValue": "6.4",
  "ratingCount": "224,460",
  "duration": "1h 57min",
  "castList": [
    "Adam Sandler",
    "Jennifer Aniston",
    "Nicole Kidman",
    "Nick Swardson",
    "Brooklyn Decker",
    "Bailee Madison",
    "Griffin Gluck",
    "Dave Matthews",
    "Kevin Nealon",
    "Rachel Dratch",
    "Allen Covert",
    "Dan Patrick",
    "Minka Kelly",
    "Jackie Sandler",
    "Rakefet Abergel"
  ],
  "characterList": [
    "Danny",
    "Katherine",
    "Devlin Adams",
    "Eddie",
    "Palmer",
    "Maggie",
    "Michael",
    "Ian Maxtone Jones",
    "Adon",
    "Kirsten Brant",
    "Soul Patch",
    "Tanner Patrick",
    "Joanna Damon",
    "Veruca",
    "Patricia"
  ],
  "directorList": [
    "Dennis Dugan"
  ]
}]